tachyconnect/GSI_Parser.py
tachyconnect/ReplyHandler.py
tachyconnect/TachyJoystick.py
tachyconnect/TachyRequest.py
tachyconnect/__init__.py
tachyconnect/gc_constants.py
tachyconnect/geo_com.py
tachyconnect/ts_control.py
tachyconnect/ui/tachy_joystick.py
tachyconnect-0.4.1.dist-info/LICENSE
tachyconnect-0.4.1.dist-info/METADATA
tachyconnect-0.4.1.dist-info/WHEEL
tachyconnect-0.4.1.dist-info/top_level.txt
tachyconnect-0.4.1.dist-info/RECORD
