Metadata-Version: 2.1
Name: tachyconnect
Version: 0.4.1
Summary: Leica total stations and Qt via python
Home-page: https://github.com/gbv/tachyconnect
Author: Christian Trapp
Author-email: trapp@gbv.de
License: UNKNOWN
Project-URL: Bug Tracker, https://github.com/gbv/tachyconnect/issues
Platform: UNKNOWN
Classifier: Programming Language :: Python :: 3
Classifier: License :: OSI Approved :: GNU General Public License v3 (GPLv3)
Classifier: Operating System :: OS Independent
Classifier: Development Status :: 4 - Beta
Requires-Python: >=3.8
License-File: LICENSE
Requires-Dist: pyqt5
